odoo/addons/shopinvader_payment_stripe/README.rst
odoo/addons/shopinvader_payment_stripe/__init__.py
odoo/addons/shopinvader_payment_stripe/__manifest__.py
odoo/addons/shopinvader_payment_stripe/demo/payment_demo.xml
odoo/addons/shopinvader_payment_stripe/i18n/shopinvader_payment_stripe.pot
odoo/addons/shopinvader_payment_stripe/readme/CONTRIBUTORS.rst
odoo/addons/shopinvader_payment_stripe/readme/DESCRIPTION.rst
odoo/addons/shopinvader_payment_stripe/services/__init__.py
odoo/addons/shopinvader_payment_stripe/services/payment_stripe.py
odoo/addons/shopinvader_payment_stripe/static/description/index.html
odoo/addons/shopinvader_payment_stripe/tests/__init__.py
odoo/addons/shopinvader_payment_stripe/tests/test_payment_stripe.py
odoo14_addon_shopinvader_payment_stripe-14.0.1.0.1.dist-info/METADATA
odoo14_addon_shopinvader_payment_stripe-14.0.1.0.1.dist-info/WHEEL
odoo14_addon_shopinvader_payment_stripe-14.0.1.0.1.dist-info/top_level.txt
odoo14_addon_shopinvader_payment_stripe-14.0.1.0.1.dist-info/RECORD
