Metadata-Version: 2.1
Name: odoo14-addon-shopinvader-payment-stripe
Version: 14.0.1.0.1
Summary: Shopinvader REST Services for Stripe Payments
Home-page: https://github.com/shopinvader/odoo-shopinvader-payment
Author: ACSONE SA/NV
License: AGPL-3
Platform: UNKNOWN
Classifier: Programming Language :: Python
Classifier: Framework :: Odoo
Classifier: License :: OSI Approved :: GNU Affero General Public License v3
Requires-Python: >=3.6
Requires-Dist: odoo14-addon-invader-payment-stripe
Requires-Dist: odoo14-addon-shopinvader-payment
Requires-Dist: odoo (<14.1dev,>=14.0a)
